{
    "$schema": "https://raw.githubusercontent.com/ScoopInstaller/Scoop/master/schema.json",
    "description": "Chat client for https://twitch.tv ",
    "bin": "chatterino.exe",
    "hash": "d5063cc15184c0073b50e69d999d02a828733f30a722812d74230bf917394b53",
    "shortcuts": [
        [
            "chatterino.exe",
            "Chatterino"
        ]
    ],
    "extract_dir": "Chatterino2",
    "version": "2.5.3",
    "url": "https://github.com/Chatterino/chatterino2/releases/download/v2.5.3/Chatterino.Portable.zip",
    "homepage": "https://github.com/Chatterino/chatterino2",
    "license": "MIT",
    "checkver": "github",
    "autoupdate": {
        "url": "https://github.com/Chatterino/chatterino2/releases/download/v$version/Chatterino.Portable.zip"
    }
}
