{
    "$schema": "https://raw.githubusercontent.com/ScoopInstaller/Scoop/master/schema.json",
    "description": "📋 Cut, copy, and paste anything, anywhere, all from the terminal. 😄 Easy, breezy, and beautiful.",
    "version": "0.2.1",
    "license": "GPL-3.0",
    "bin": "clipboard.exe",
    "homepage": "https://github.com/Slackadays/Clipboard/",
    "url": "https://github.com/Slackadays/Clipboard/releases/download/0.2.1/clipboard-windows-amd64.zip",
    "extract_dir": "bin",
    "hash": "45e5e4be41c95ae55233550e3da56c75b5db56372779c51f52f2e97b5fba977e",
    "autoupdate": {
        "url": "https://github.com/Slackadays/Clipboard/releases/download/$version/clipboard-windows-amd64.zip"
    },
    "checkver": "github"
}