{
    "version": "1.0.0",
    "description": "Lightweight program to download gitignore templates from gitignore.io",
    "homepage": "https://github.com/jewlexx/quickignore",
    "bin": "quickignore.exe",
    "url": "https://github.com/jewlexx/quickignore/releases/download/v1.0.0/quickignore.exe",
    "hash": "a9d5ea62833971651396e4fbb5cd5059212afec6f1d0d39f955a95beb2f289ab",
    "checkver": "github",
    "autoupdate": {
        "url": "https://github.com/jewlexx/quickignore/releases/download/v$version/quickignore.exe"
    },
    "license": "MIT"
}