{
    "license": "GPL-3.0",
    "description": "An installer for Hollow Knight mods written in Avalonia.",
    "hash": "4543c5643a4b7c8bec883a06c62bde1e3f48ceba6d7f7da96e98a6e91bc486dc",
    "bin": "Scarab.exe",
    "version": "2.3.0.0",
    "url": "https://github.com/fifty-six/Scarab/releases/download/v2.3.0.0/windows.zip",
    "homepage": "https://github.com/fifty-six/Scarab",
    "checkver": "github",
    "autoupdate": {
        "url": "https://github.com/fifty-six/Scarab/releases/download/v$version/windows.zip"
    }
}
